<annotation>
	<folder>unlabeled</folder>
	<filename>IMG_20210113_134358691.jpg</filename>
	<path>/home/chrash/docs/work/homework/box-detector/data/unlabeled/IMG_20210113_134358691.jpg</path>
	<source>
		<database>Unknown</database>
	</source>
	<size>
		<width>3472</width>
		<height>4640</height>
		<depth>3</depth>
	</size>
	<segmented>0</segmented>
	<object>
		<name>Honey Smacks</name>
		<pose>Unspecified</pose>
		<truncated>0</truncated>
		<difficult>0</difficult>
		<bndbox>
			<xmin>95</xmin>
			<ymin>600</ymin>
			<xmax>547</xmax>
			<ymax>1252</ymax>
		</bndbox>
	</object>
	<object>
		<name>Honey Smacks</name>
		<pose>Unspecified</pose>
		<truncated>0</truncated>
		<difficult>0</difficult>
		<bndbox>
			<xmin>504</xmin>
			<ymin>571</ymin>
			<xmax>966</xmax>
			<ymax>1243</ymax>
		</bndbox>
	</object>
	<object>
		<name>Golden Grahams</name>
		<pose>Unspecified</pose>
		<truncated>0</truncated>
		<difficult>0</difficult>
		<bndbox>
			<xmin>904</xmin>
			<ymin>686</ymin>
			<xmax>1423</xmax>
			<ymax>1238</ymax>
		</bndbox>
	</object>
	<object>
		<name>Golden Grahams</name>
		<pose>Unspecified</pose>
		<truncated>0</truncated>
		<difficult>0</difficult>
		<bndbox>
			<xmin>1352</xmin>
			<ymin>595</ymin>
			<xmax>1904</xmax>
			<ymax>1205</ymax>
		</bndbox>
	</object>
	<object>
		<name>Cinnamon Toast Crunch</name>
		<pose>Unspecified</pose>
		<truncated>0</truncated>
		<difficult>0</difficult>
		<bndbox>
			<xmin>490</xmin>
			<ymin>1357</ymin>
			<xmax>1042</xmax>
			<ymax>2086</ymax>
		</bndbox>
	</object>
	<object>
		<name>Cinnamon Toast Crunch</name>
		<pose>Unspecified</pose>
		<truncated>0</truncated>
		<difficult>0</difficult>
		<bndbox>
			<xmin>980</xmin>
			<ymin>1324</ymin>
			<xmax>1557</xmax>
			<ymax>2057</ymax>
		</bndbox>
	</object>
	<object>
		<name>Cinnamon Toast Crunch</name>
		<pose>Unspecified</pose>
		<truncated>1</truncated>
		<difficult>0</difficult>
		<bndbox>
			<xmin>1</xmin>
			<ymin>1386</ymin>
			<xmax>523</xmax>
			<ymax>2110</ymax>
		</bndbox>
	</object>
	<object>
		<name>Cinnamon Toast Crunch</name>
		<pose>Unspecified</pose>
		<truncated>0</truncated>
		<difficult>0</difficult>
		<bndbox>
			<xmin>319</xmin>
			<ymin>2319</ymin>
			<xmax>823</xmax>
			<ymax>2986</ymax>
		</bndbox>
	</object>
	<object>
		<name>Cinnamon Toast Crunch</name>
		<pose>Unspecified</pose>
		<truncated>0</truncated>
		<difficult>0</difficult>
		<bndbox>
			<xmin>57</xmin>
			<ymin>3305</ymin>
			<xmax>657</xmax>
			<ymax>4014</ymax>
		</bndbox>
	</object>
	<object>
		<name>Cinnamon Toast Crunch</name>
		<pose>Unspecified</pose>
		<truncated>0</truncated>
		<difficult>0</difficult>
		<bndbox>
			<xmin>619</xmin>
			<ymin>3252</ymin>
			<xmax>1242</xmax>
			<ymax>3981</ymax>
		</bndbox>
	</object>
	<object>
		<name>Cinnamon Toast Crunch</name>
		<pose>Unspecified</pose>
		<truncated>0</truncated>
		<difficult>0</difficult>
		<bndbox>
			<xmin>1328</xmin>
			<ymin>3105</ymin>
			<xmax>1776</xmax>
			<ymax>3667</ymax>
		</bndbox>
	</object>
	<object>
		<name>Cinnamon Toast Crunch</name>
		<pose>Unspecified</pose>
		<truncated>0</truncated>
		<difficult>0</difficult>
		<bndbox>
			<xmin>1738</xmin>
			<ymin>3067</ymin>
			<xmax>2219</xmax>
			<ymax>3624</ymax>
		</bndbox>
	</object>
	<object>
		<name>Cinnamon Toast Crunch</name>
		<pose>Unspecified</pose>
		<truncated>1</truncated>
		<difficult>0</difficult>
		<bndbox>
			<xmin>1247</xmin>
			<ymin>3905</ymin>
			<xmax>1852</xmax>
			<ymax>4640</ymax>
		</bndbox>
	</object>
	<object>
		<name>Cinnamon Toast Crunch</name>
		<pose>Unspecified</pose>
		<truncated>0</truncated>
		<difficult>0</difficult>
		<bndbox>
			<xmin>1766</xmin>
			<ymin>3852</ymin>
			<xmax>2380</xmax>
			<ymax>4633</ymax>
		</bndbox>
	</object>
	<object>
		<name>Cinnamon Toast Crunch</name>
		<pose>Unspecified</pose>
		<truncated>0</truncated>
		<difficult>0</difficult>
		<bndbox>
			<xmin>2328</xmin>
			<ymin>3810</ymin>
			<xmax>2971</xmax>
			<ymax>4524</ymax>
		</bndbox>
	</object>
	<object>
		<name>Cinnamon Toast Crunch</name>
		<pose>Unspecified</pose>
		<truncated>1</truncated>
		<difficult>0</difficult>
		<bndbox>
			<xmin>2866</xmin>
			<ymin>3757</ymin>
			<xmax>3472</xmax>
			<ymax>4471</ymax>
		</bndbox>
	</object>
	<object>
		<name>Lucky Charms</name>
		<pose>Unspecified</pose>
		<truncated>0</truncated>
		<difficult>0</difficult>
		<bndbox>
			<xmin>2790</xmin>
			<ymin>2119</ymin>
			<xmax>3290</xmax>
			<ymax>2738</ymax>
		</bndbox>
	</object>
	<object>
		<name>Great Value Cinnamon Crunch</name>
		<pose>Unspecified</pose>
		<truncated>0</truncated>
		<difficult>0</difficult>
		<bndbox>
			<xmin>776</xmin>
			<ymin>2214</ymin>
			<xmax>1238</xmax>
			<ymax>2971</ymax>
		</bndbox>
	</object>
	<object>
		<name>Great Value Cinnamon Crunch</name>
		<pose>Unspecified</pose>
		<truncated>0</truncated>
		<difficult>0</difficult>
		<bndbox>
			<xmin>1219</xmin>
			<ymin>2186</ymin>
			<xmax>1671</xmax>
			<ymax>2910</ymax>
		</bndbox>
	</object>
	<object>
		<name>Trix</name>
		<pose>Unspecified</pose>
		<truncated>0</truncated>
		<difficult>0</difficult>
		<bndbox>
			<xmin>1509</xmin>
			<ymin>1324</ymin>
			<xmax>2047</xmax>
			<ymax>2029</ymax>
		</bndbox>
	</object>
	<object>
		<name>Trix</name>
		<pose>Unspecified</pose>
		<truncated>0</truncated>
		<difficult>0</difficult>
		<bndbox>
			<xmin>2009</xmin>
			<ymin>1314</ymin>
			<xmax>2533</xmax>
			<ymax>1957</ymax>
		</bndbox>
	</object>
	<object>
		<name>Froot Loops</name>
		<pose>Unspecified</pose>
		<truncated>0</truncated>
		<difficult>0</difficult>
		<bndbox>
			<xmin>2404</xmin>
			<ymin>1252</ymin>
			<xmax>2919</xmax>
			<ymax>1933</ymax>
		</bndbox>
	</object>
</annotation>
